reachy2_sdk/__init__.py
reachy2_sdk/reachy_sdk.py
reachy2_sdk/components/__init__.py
reachy2_sdk/components/antenna.py
reachy2_sdk/components/goto_based_component.py
reachy2_sdk/config/__init__.py
reachy2_sdk/config/reachy_info.py
reachy2_sdk/dynamixel/__init__.py
reachy2_sdk/dynamixel/dynamixel_motor.py
reachy2_sdk/grippers/__init__.py
reachy2_sdk/grippers/gripper_joint.py
reachy2_sdk/grippers/parallel_gripper.py
reachy2_sdk/media/__init__.py
reachy2_sdk/media/audio.py
reachy2_sdk/media/camera.py
reachy2_sdk/media/camera_manager.py
reachy2_sdk/orbita/__init__.py
reachy2_sdk/orbita/orbita.py
reachy2_sdk/orbita/orbita2d.py
reachy2_sdk/orbita/orbita3d.py
reachy2_sdk/orbita/orbita_axis.py
reachy2_sdk/orbita/orbita_joint.py
reachy2_sdk/orbita/orbita_motor.py
reachy2_sdk/orbita/utils.py
reachy2_sdk/parts/__init__.py
reachy2_sdk/parts/arm.py
reachy2_sdk/parts/goto_based_part.py
reachy2_sdk/parts/hand.py
reachy2_sdk/parts/head.py
reachy2_sdk/parts/joints_based_part.py
reachy2_sdk/parts/mobile_base.py
reachy2_sdk/parts/part.py
reachy2_sdk/parts/tripod.py
reachy2_sdk/sensors/__init__.py
reachy2_sdk/sensors/lidar.py
reachy2_sdk/utils/__init__.py
reachy2_sdk/utils/custom_dict.py
reachy2_sdk/utils/goto_based_element.py
reachy2_sdk/utils/utils.py
reachy2_sdk-1.0.14.dist-info/licenses/LICENSE
reachy2_sdk-1.0.14.dist-info/METADATA
reachy2_sdk-1.0.14.dist-info/WHEEL
reachy2_sdk-1.0.14.dist-info/top_level.txt
reachy2_sdk-1.0.14.dist-info/zip-safe
reachy2_sdk-1.0.14.dist-info/RECORD
