Metadata-Version: 2.4
Name: reachy2-sdk
Version: 1.0.14
Summary: Reachy 2 SDK
Home-page: https://github.com/pollen-robotics/reachy2-sdk
Author: Pollen Robotics
Author-email: contact@pollen-robotics.com
License-File: LICENSE
Requires-Dist: packaging
Requires-Dist: numpy<2.3.0,>=1.24.0
Requires-Dist: protobuf<=6.32.0,>=4.25.0
Requires-Dist: grpcio<=1.73.1,>=1.59.0
Requires-Dist: pyquaternion==0.9.9
Requires-Dist: opencv-python<5.0.0,>=4.8.0
Requires-Dist: reachy2-sdk-api<1.1.0,>=1.0.19
Provides-Extra: dev
Requires-Dist: black==23.12.1; extra == "dev"
Requires-Dist: flake8==7.0.0; extra == "dev"
Requires-Dist: pytest==7.4.3; extra == "dev"
Requires-Dist: coverage==7.3.2; extra == "dev"
Requires-Dist: mypy==1.8.0; extra == "dev"
Requires-Dist: isort==5.13.2; extra == "dev"
Requires-Dist: types-protobuf<=4.25.3,>=4.24.0; extra == "dev"
Requires-Dist: pdoc<=14.4.0,>=14.0.0; extra == "dev"
Requires-Dist: pydocstyle==6.3.0; extra == "dev"
Provides-Extra: examples
Requires-Dist: pillow==10.4.0; extra == "examples"
Dynamic: license-file
